{
  "version": "6",
  "dialect": "sqlite",
  "id": "e0383956-0aef-4a91-95d4-bc38f613571f",
  "prevId": "8e5df21c-dfb1-4470-a67c-2edb12c65f95",
  "tables": {
    "apiKeys": {
      "name": "apiKeys",
      "columns": {
        "value": {
          "name": "value",
          "type": "text",
          "primaryKey": false,
          "notNull": true,
          "autoincrement": false
        },
        "name": {
          "name": "name",
          "type": "text",
          "primaryKey": false,
          "notNull": true,
          "autoincrement": false
        },
        "userId": {
          "name": "userId",
          "type": "text(255)",
          "primaryKey": false,
          "notNull": true,
          "autoincrement": false
        },
        "id": {
          "name": "id",
          "type": "text",
          "primaryKey": true,
          "notNull": true,
          "autoincrement": false
        },
        "createdAt": {
          "name": "createdAt",
          "type": "text",
          "primaryKey": false,
          "notNull": false,
          "autoincrement": false,
          "default": "CURRENT_TIMESTAMP"
        }
      },
      "indexes": {
        "apiKeys_userId_unique": {
          "name": "apiKeys_userId_unique",
          "columns": ["userId"],
          "isUnique": true
        }
      },
      "foreignKeys": {
        "apiKeys_userId_users_id_fk": {
          "name": "apiKeys_userId_users_id_fk",
          "tableFrom": "apiKeys",
          "tableTo": "users",
          "columnsFrom": ["userId"],
          "columnsTo": ["id"],
          "onDelete": "no action",
          "onUpdate": "no action"
        }
      },
      "compositePrimaryKeys": {},
      "uniqueConstraints": {}
    },
    "publications": {
      "name": "publications",
      "columns": {
        "id": {
          "name": "id",
          "type": "text",
          "primaryKey": true,
          "notNull": true,
          "autoincrement": false
        },
        "createdAt": {
          "name": "createdAt",
          "type": "text",
          "primaryKey": false,
          "notNull": false,
          "autoincrement": false,
          "default": "CURRENT_TIMESTAMP"
        },
        "name": {
          "name": "name",
          "type": "text",
          "primaryKey": false,
          "notNull": true,
          "autoincrement": false
        },
        "status": {
          "name": "status",
          "type": "text",
          "primaryKey": false,
          "notNull": true,
          "autoincrement": false,
          "default": "'DRAFT'"
        },
        "userId": {
          "name": "userId",
          "type": "text(255)",
          "primaryKey": false,
          "notNull": true,
          "autoincrement": false
        }
      },
      "indexes": {},
      "foreignKeys": {
        "publications_userId_users_id_fk": {
          "name": "publications_userId_users_id_fk",
          "tableFrom": "publications",
          "tableTo": "users",
          "columnsFrom": ["userId"],
          "columnsTo": ["id"],
          "onDelete": "no action",
          "onUpdate": "no action"
        }
      },
      "compositePrimaryKeys": {},
      "uniqueConstraints": {}
    },
    "users": {
      "name": "users",
      "columns": {
        "id": {
          "name": "id",
          "type": "text",
          "primaryKey": true,
          "notNull": true,
          "autoincrement": false
        },
        "createdAt": {
          "name": "createdAt",
          "type": "text",
          "primaryKey": false,
          "notNull": false,
          "autoincrement": false,
          "default": "CURRENT_TIMESTAMP"
        },
        "name": {
          "name": "name",
          "type": "text",
          "primaryKey": false,
          "notNull": true,
          "autoincrement": false
        },
        "email": {
          "name": "email",
          "type": "text",
          "primaryKey": false,
          "notNull": true,
          "autoincrement": false
        },
        "profilePictureUrl": {
          "name": "profilePictureUrl",
          "type": "text",
          "primaryKey": false,
          "notNull": false,
          "autoincrement": false
        }
      },
      "indexes": {},
      "foreignKeys": {},
      "compositePrimaryKeys": {},
      "uniqueConstraints": {}
    }
  },
  "enums": {},
  "_meta": {
    "schemas": {},
    "tables": {},
    "columns": {}
  },
  "internal": {
    "indexes": {}
  }
}
